pyneurotrace/__init__.py
pyneurotrace/analysis.py
pyneurotrace/events.py
pyneurotrace/files.py
pyneurotrace/filters.py
pyneurotrace/morphology.py
pyneurotrace/nndFilter.py
pyneurotrace/notebook.py
pyneurotrace/viz.py
pyneurotrace/gpu/__init__.py
pyneurotrace/gpu/events.py
pyneurotrace/gpu/filters.py
pyNeuroTrace-1.0.1.dist-info/LICENSE
pyNeuroTrace-1.0.1.dist-info/METADATA
pyNeuroTrace-1.0.1.dist-info/WHEEL
pyNeuroTrace-1.0.1.dist-info/dependency_links.txt
pyNeuroTrace-1.0.1.dist-info/top_level.txt
pyNeuroTrace-1.0.1.dist-info/RECORD
