Metadata-Version: 2.1
Name: pyNeuroTrace
Version: 1.0.1
Summary: Python code for neural time series
Home-page: https://github.com/padster/pyNeuroTrace
Author: Pat Coleman
Author-email: Pat Coleman <padsterpat@gmail.com>, Peter Hogg <peter.hogg@ubc.ca>
Project-URL: Homepage, https://github.com/padster/pyNeuroTrace
Project-URL: Issues, https://github.com/padster/pyNeuroTrace/issues
Keywords: neuron,analysis,timeseries,neuroscience
Classifier: Programming Language :: Python :: 3
Classifier: License :: OSI Approved :: Mozilla Public License 2.0 (MPL 2.0)
Classifier: Operating System :: OS Independent
Requires-Python: >=3.9
License-File: LICENSE
Requires-Dist: setuptools >=70.0.0
Requires-Dist: ipython
Requires-Dist: ipywidgets
Requires-Dist: matplotlib
Requires-Dist: matplotlib-scalebar
Requires-Dist: numpy <2.0.0
Requires-Dist: pytest
Requires-Dist: PyQt5
Requires-Dist: scipy
Requires-Dist: tqdm
Provides-Extra: gpu
Requires-Dist: cupy ; extra == 'gpu'
